{
  "stats": {
    "tconstruct:binding": {},
    "tconstruct:grip": {
      "accuracy": 0.0,
      "durability": -0.2,
      "melee_damage": 2.0
    },
    "tconstruct:handle": {
      "durability": -0.5,
      "melee_damage": 0.3,
      "melee_speed": 0.0,
      "mining_speed": 0.3
    },
    "tconstruct:head": {
      "durability": 20,
      "melee_attack": 3.0,
      "mining_speed": 6.0,
      "mining_tier": "minecraft:wood"
    },
    "tconstruct:limb": {
      "accuracy": 0.0,
      "draw_speed": 0.3,
      "durability": 10,
      "velocity": 0.4
    },
    "tconstruct:maille": {},
    "tconstruct:plating_boots": {
      "armor": 1.0,
      "durability": 1
    },
    "tconstruct:plating_chestplate": {
      "armor": 2.5,
      "durability": 1
    },
    "tconstruct:plating_helmet": {
      "armor": 1.0,
      "durability": 1
    },
    "tconstruct:plating_leggings": {
      "armor": 2.0,
      "durability": 1
    },
    "tconstruct:plating_shield": {
      "durability": 1
    },
    "tconstruct:skull": {
      "armor": 1,
      "durability": 1
    }
  }
}