{
	"elements": [
		{
			"weight": 1.0,
			"key": {
				"float": true,
				"laggy": true,
				"Name": "waystones:black_sharestone",
				"top": true,
				"full": false
			}
		},
		{
			"weight": 1.0,
			"key": {
				"float": true,
				"laggy": true,
				"Name": "waystones:blackstone_waystone",
				"top": true,
				"full": false
			}
		},
		{
			"weight": 1.0,
			"key": {
				"float": true,
				"laggy": true,
				"Name": "waystones:blue_sharestone",
				"top": true,
				"full": false
			}
		},
		{
			"weight": 1.0,
			"key": {
				"float": true,
				"laggy": true,
				"Name": "waystones:brown_sharestone",
				"top": true,
				"full": false
			}
		},
		{
			"weight": 1.0,
			"key": {
				"float": true,
				"laggy": true,
				"Name": "waystones:cyan_sharestone",
				"top": true,
				"full": false
			}
		},
		{
			"weight": 1.0,
			"key": {
				"float": true,
				"laggy": true,
				"Name": "waystones:deepslate_waystone",
				"top": true,
				"full": false
			}
		},
		{
			"weight": 1.0,
			"key": {
				"float": true,
				"laggy": true,
				"Name": "waystones:end_stone_waystone",
				"top": true,
				"full": false
			}
		},
		{
			"weight": 1.0,
			"key": {
				"float": true,
				"laggy": true,
				"Name": "waystones:gray_sharestone",
				"top": true,
				"full": false
			}
		},
		{
			"weight": 1.0,
			"key": {
				"float": true,
				"laggy": true,
				"Name": "waystones:green_sharestone",
				"top": true,
				"full": false
			}
		},
		{
			"weight": 1.0,
			"key": {
				"float": true,
				"laggy": true,
				"Name": "waystones:light_blue_sharestone",
				"top": true,
				"full": false
			}
		},
		{
			"weight": 1.0,
			"key": {
				"float": true,
				"laggy": true,
				"Name": "waystones:light_gray_sharestone",
				"top": true,
				"full": false
			}
		},
		{
			"weight": 1.0,
			"key": {
				"float": true,
				"laggy": true,
				"Name": "waystones:lime_sharestone",
				"top": true,
				"full": false
			}
		},
		{
			"weight": 1.0,
			"key": {
				"float": true,
				"laggy": true,
				"Name": "waystones:magenta_sharestone",
				"top": true,
				"full": false
			}
		},
		{
			"weight": 1.0,
			"key": {
				"float": true,
				"laggy": true,
				"Name": "waystones:mossy_waystone",
				"top": true,
				"full": false
			}
		},
		{
			"weight": 1.0,
			"key": {
				"float": true,
				"laggy": true,
				"Name": "waystones:orange_sharestone",
				"top": true,
				"full": false
			}
		},
		{
			"weight": 1.0,
			"key": {
				"float": true,
				"laggy": true,
				"Name": "waystones:pink_sharestone",
				"top": true,
				"full": false
			}
		},
		{
			"weight": 1.0,
			"key": {
				"float": true,
				"laggy": true,
				"Name": "waystones:portstone",
				"top": true,
				"full": false
			}
		},
		{
			"weight": 1.0,
			"key": {
				"float": true,
				"laggy": true,
				"Name": "waystones:purple_sharestone",
				"top": true,
				"full": false
			}
		},
		{
			"weight": 1.0,
			"key": {
				"float": true,
				"laggy": true,
				"Name": "waystones:red_sharestone",
				"top": true,
				"full": false
			}
		},
		{
			"weight": 1.0,
			"key": {
				"float": true,
				"laggy": true,
				"Name": "waystones:sandy_waystone",
				"top": true,
				"full": false
			}
		},
		{
			"weight": 1.0,
			"key": {
				"float": true,
				"laggy": true,
				"Name": "waystones:sharestone",
				"top": true,
				"full": false
			}
		},
		{
			"weight": 1.0,
			"key": {
				"float": true,
				"laggy": true,
				"Name": "waystones:warp_plate",
				"top": true,
				"full": false
			}
		},
		{
			"weight": 1.0,
			"key": {
				"float": true,
				"laggy": true,
				"Name": "waystones:waystone",
				"top": true,
				"full": false
			}
		},
		{
			"weight": 1.0,
			"key": {
				"float": true,
				"laggy": true,
				"Name": "waystones:white_sharestone",
				"top": true,
				"full": false
			}
		},
		{
			"weight": 1.0,
			"key": {
				"float": true,
				"laggy": true,
				"Name": "waystones:yellow_sharestone",
				"top": true,
				"full": false
			}
		}
	]
}
